canopyhydro/Cylinder.py
canopyhydro/CylinderCollection.py
canopyhydro/DataClasses.py
canopyhydro/Forester.py
canopyhydro/__init__.py
canopyhydro/canopyhydro_config.toml
canopyhydro/configuration.py
canopyhydro/geometry.py
canopyhydro/handlers.py
canopyhydro/import_options.py
canopyhydro/local.py
canopyhydro/logging_config.yml
canopyhydro/utils.py
canoPyHydro-0.1.1.dist-info/METADATA
canoPyHydro-0.1.1.dist-info/WHEEL
canoPyHydro-0.1.1.dist-info/top_level.txt
canoPyHydro-0.1.1.dist-info/RECORD
