Metadata-Version: 2.1
Name: canoPyHydro
Version: 0.1.1
Summary: An Innovative Approach to Vegetative Precipitation Partitioning
Author-email: Collin Wischmeyer <cjwischmeyer@gmail.com>, Travis Swanson <travis.swanson@gmail.com>, John Van Stan <j.vanstan@csuohio.edu>
Project-URL: Documentation, https://canopyhydrodynamics.readthedocs.io/main/
Project-URL: Source, https://github.com/wischmcj/canopyHydrodynamics/
Classifier: Programming Language :: Python :: 3
Classifier: License :: OSI Approved :: Mozilla Public License 2.0 (MPL 2.0)
Classifier: Topic :: Scientific/Engineering :: Hydrology
Classifier: Topic :: Scientific/Engineering :: Image Processing
Classifier: Intended Audience :: Science/Research
Classifier: Development Status :: 5 - Production/Stable
Requires-Python: >=3.9.1
Requires-Dist: geopandas ==1.0.1
Requires-Dist: matplotlib ==3.9.2
Requires-Dist: networkx ==3.4.1
Requires-Dist: numpy <2,>=1.16.0
Requires-Dist: pyyaml ==6.0.2
Requires-Dist: rich ==13.9.2
Requires-Dist: ruff ==0.5.1
Requires-Dist: scipy ==1.13.1
Requires-Dist: Shapely ==2.0.6
Requires-Dist: toml ==0.10.2
Requires-Dist: jupytext ==1.16.4
Requires-Dist: open3d ==0.18.0
Requires-Dist: PyQt6 ==6.7.1
Provides-Extra: test
Requires-Dist: jupytext ==1.16.2 ; extra == 'test'
Requires-Dist: pytest ==8.3.3 ; extra == 'test'
Requires-Dist: ruff ==0.5.1 ; extra == 'test'
Requires-Dist: pre-commit ==4.0.1 ; extra == 'test'
Requires-Dist: myst-parser ==4.0.0 ; extra == 'test'
Requires-Dist: pandoc ==2.4 ; extra == 'test'
Requires-Dist: sphinx ==8.1.3 ; extra == 'test'
Requires-Dist: sphinx-rtd-theme ==3.0.1 ; extra == 'test'
Requires-Dist: sphinxcontrib-napoleon ==0.7.2 ; extra == 'test'
Requires-Dist: nbsphinx ==0.9.5 ; extra == 'test'
Requires-Dist: ipykernel ==6.25.9 ; extra == 'test'
